boldigger_cline/__init__.py
boldigger_cline/__main__.py
boldigger_cline/additional_data.py
boldigger_cline/api_verification.py
boldigger_cline/boldblast_coi.py
boldigger_cline/boldblast_its.py
boldigger_cline/boldblast_rbcl.py
boldigger_cline/digger_sort.py
boldigger_cline/first_hit.py
boldigger_cline/jamp_hit.py
boldigger_cline/login.py
boldigger_cline/data/certs.pem
boldigger_cline-2.2.3.dist-info/LICENSE
boldigger_cline-2.2.3.dist-info/METADATA
boldigger_cline-2.2.3.dist-info/WHEEL
boldigger_cline-2.2.3.dist-info/entry_points.txt
boldigger_cline-2.2.3.dist-info/top_level.txt
boldigger_cline-2.2.3.dist-info/RECORD
