Metadata-Version: 2.1
Name: boldigger-cline
Version: 2.2.3
Summary: BOLDigger as a command-line tool
Home-page: https://github.com/DominikBuchner/BOLDigger-commandline
Author: Dominik Buchner
Author-email: dominik.buchner524@googlemail.com
License: MIT
Classifier: Programming Language :: Python :: 3
Classifier: License :: OSI Approved :: MIT License
Classifier: Operating System :: OS Independent
Requires-Python: >=3.6
License-File: LICENSE
Requires-Dist: tqdm >=4.32.2
Requires-Dist: boldigger >=2.2.1
